.gitignore
Makefile
README.md
VERSION
setup.cfg
setup.py
./VERSION
.gitlab/ci.yaml
bin/octomy-clockwork
code_quality/.flake8
code_quality/Makefile
code_quality/mypy.ini
code_quality/pylintrc
design/logo-1024.png
design/logo-1024.svg
fk/clockwork/__init__.py
fk/clockwork/cron.py
fk/clockwork/db.py
fk/clockwork/processor.py
fk/clockwork/server.py
octomy_clockwork.egg-info/PKG-INFO
octomy_clockwork.egg-info/SOURCES.txt
octomy_clockwork.egg-info/dependency_links.txt
octomy_clockwork.egg-info/requires.txt
octomy_clockwork.egg-info/top_level.txt
octomy_clockwork.egg-info/zip-safe
requirements/requirements.in
requirements/requirements.txt
requirements/test_requirements.in
requirements/test_requirements.txt
tests/Makefile
tests/__init__.py
tests/pytest.ini
tests/integration/__init__.py
tests/integration/test_integration.py
tests/load/__init__.py
tests/load/test_load.py
tests/regressions/__init__.py
tests/regressions/test_regressions.py
tests/unit/__init__.py
tests/unit/test_unit.py